{
  "users": [
    {
      "name": "sanya​",
      "results": [
        {
          "score": 5,
          "misses": 3
        },
        {
          "score": 5,
          "misses": 0
        },
        {
          "score": 5,
          "misses": 0
        },
        {
          "score": 5,
          "misses": 2
        },
        {
          "score": 12,
          "misses": 7
        },
        {
          "score": 5,
          "misses": 0
        },
        {
          "score": 5,
          "misses": 4
        },
        {
          "score": 5,
          "misses": 2
        }
      ]
    },
    {
      "name": "vasya​",
      "results": [
        {
          "score": 5,
          "misses": 0
        },
        {
          "score": 5,
          "misses": 1
        },
        {
          "score": 5,
          "misses": 3
        }
      ]
    },
    {
      "name": "test_start​",
      "results": [
        {
          "score": 5,
          "misses": 5
        },
        {
          "score": 5,
          "misses": 3
        },
        {
          "score": 5,
          "misses": 2
        },
        {
          "score": 5,
          "misses": 4
        },
        {
          "score": 5,
          "misses": 3
        },
        {
          "score": 5,
          "misses": 2
        },
        {
          "score": 5,
          "misses": 2
        },
        {
          "score": 12,
          "misses": 16
        },
        {
          "score": 12,
          "misses": 10
        },
        {
          "score": 12,
          "misses": 13
        },
        {
          "score": 12,
          "misses": 14
        },
        {
          "score": 12,
          "misses": 11
        },
        {
          "score": 12,
          "misses": 9
        },
        {
          "score": 12,
          "misses": 11
        },
        {
          "score": 18,
          "misses": 37
        },
        {
          "score": 18,
          "misses": 33
        },
        {
          "score": 18,
          "misses": 35
        },
        {
          "score": 18,
          "misses": 25
        },
        {
          "score": 18,
          "misses": 27
        },
        {
          "score": 18,
          "misses": 30
        },
        {
          "score": 18,
          "misses": 23
        },
        {
          "score": 25,
          "misses": 55
        },
        {
          "score": 25,
          "misses": 50
        },
        {
          "score": 25,
          "misses": 47
        },
        {
          "score": 25,
          "misses": 52
        },
        {
          "score": 25,
          "misses": 40
        },
        {
          "score": 25,
          "misses": 37
        },
        {
          "score": 25,
          "misses": 34
        }
      ]
    },
    {
      "name": "test_end​",
      "results": [
        {
          "score": 5,
          "misses": 2
        },
        {
          "score": 5,
          "misses": 0
        },
        {
          "score": 5,
          "misses": 1
        },
        {
          "score": 5,
          "misses": 0
        },
        {
          "score": 5,
          "misses": 0
        },
        {
          "score": 5,
          "misses": 0
        },
        {
          "score": 5,
          "misses": 0
        },
        {
          "score": 12,
          "misses": 8
        },
        {
          "score": 12,
          "misses": 5
        },
        {
          "score": 12,
          "misses": 6
        },
        {
          "score": 12,
          "misses": 4
        },
        {
          "score": 12,
          "misses": 5
        },
        {
          "score": 12,
          "misses": 4
        },
        {
          "score": 12,
          "misses": 3
        },
        {
          "score": 18,
          "misses": 19
        },
        {
          "score": 18,
          "misses": 14
        },
        {
          "score": 18,
          "misses": 17
        },
        {
          "score": 18,
          "misses": 14
        },
        {
          "score": 18,
          "misses": 16
        },
        {
          "score": 18,
          "misses": 14
        },
        {
          "score": 18,
          "misses": 11
        },
        {
          "score": 25,
          "misses": 29
        },
        {
          "score": 25,
          "misses": 31
        },
        {
          "score": 25,
          "misses": 21
        },
        {
          "score": 25,
          "misses": 27
        },
        {
          "score": 25,
          "misses": 21
        },
        {
          "score": 25,
          "misses": 24
        },
        {
          "score": 25,
          "misses": 22
        }
      ]
    },
    {
      "name": "roflan​",
      "results": [
        {
          "score": 5,
          "misses": 1
        }
      ]
    },
    {
      "name": "alex​",
      "results": [
        {
          "score": 5,
          "misses": 1
        },
        {
          "score": 5,
          "misses": 1
        }
      ]
    },
    {
      "name": "ira​",
      "results": [
        {
          "score": 5,
          "misses": 1
        }
      ]
    }
  ]
}